lifxtools/__init__.py
lifxtools/__main__.py
lifxtools/color_presets.py
lifxtools/lightshow.py
lifxtools/manageddevice.py
lifxtools/managedlifx.py
lifxtools/managedlight.py
lifxtools/managedtilechain.py
lifxtools/scene.py
lifxtools/lt/__init__.py
lifxtools-0.3.2.dist-info/LICENSE
lifxtools-0.3.2.dist-info/METADATA
lifxtools-0.3.2.dist-info/WHEEL
lifxtools-0.3.2.dist-info/entry_points.txt
lifxtools-0.3.2.dist-info/top_level.txt
lifxtools-0.3.2.dist-info/RECORD
