Metadata-Version: 2.1
Name: lifxtools
Version: 0.3.2
Summary: Graphical interface for controlling lifx bulbs
Home-page: https://github.com/DrTexx/lifxtools
Author: Denver P
License: UNKNOWN
Project-URL: Bug Reports, https://github.com/DrTexx/lifxtools/issues
Project-URL: Source, https://github.com/DrTexx/lifxtools/
Platform: UNKNOWN
Classifier: Development Status :: 4 - Beta
Classifier: Intended Audience :: End Users/Desktop
Classifier: Topic :: Home Automation
Classifier: License :: OSI Approved :: GNU General Public License v3 or later (GPLv3+)
Classifier: Programming Language :: Python :: 3
Requires-Dist: wheel
Requires-Dist: bitstring (==3.1.6)
Requires-Dist: lifxlan (==1.2.5)
Requires-Dist: netifaces (==0.10.9)
Requires-Dist: colorama (==0.4.1)
Requires-Dist: numpy (==1.17.0)
Requires-Dist: PyAudio (==0.2.11)
